odoo/addons/stock_inventory_discrepancy/README.rst
odoo/addons/stock_inventory_discrepancy/__init__.py
odoo/addons/stock_inventory_discrepancy/__manifest__.py
odoo/addons/stock_inventory_discrepancy/i18n/cs_CZ.po
odoo/addons/stock_inventory_discrepancy/i18n/de.po
odoo/addons/stock_inventory_discrepancy/i18n/es.po
odoo/addons/stock_inventory_discrepancy/i18n/es_ES.po
odoo/addons/stock_inventory_discrepancy/i18n/fr.po
odoo/addons/stock_inventory_discrepancy/i18n/fr_FR.po
odoo/addons/stock_inventory_discrepancy/i18n/hr.po
odoo/addons/stock_inventory_discrepancy/i18n/it.po
odoo/addons/stock_inventory_discrepancy/i18n/nl.po
odoo/addons/stock_inventory_discrepancy/i18n/nl_NL.po
odoo/addons/stock_inventory_discrepancy/i18n/pt_BR.po
odoo/addons/stock_inventory_discrepancy/i18n/sl.po
odoo/addons/stock_inventory_discrepancy/i18n/stock_inventory_discrepancy.pot
odoo/addons/stock_inventory_discrepancy/i18n/tr_TR.po
odoo/addons/stock_inventory_discrepancy/models/__init__.py
odoo/addons/stock_inventory_discrepancy/models/stock_inventory.py
odoo/addons/stock_inventory_discrepancy/models/stock_inventory_line.py
odoo/addons/stock_inventory_discrepancy/models/stock_location.py
odoo/addons/stock_inventory_discrepancy/models/stock_warehouse.py
odoo/addons/stock_inventory_discrepancy/security/stock_inventory_discrepancy_security.xml
odoo/addons/stock_inventory_discrepancy/static/description/icon.png
odoo/addons/stock_inventory_discrepancy/tests/__init__.py
odoo/addons/stock_inventory_discrepancy/tests/test_inventory_discrepancy.py
odoo/addons/stock_inventory_discrepancy/views/stock_inventory_view.xml
odoo/addons/stock_inventory_discrepancy/views/stock_location_view.xml
odoo/addons/stock_inventory_discrepancy/views/stock_warehouse_view.xml
odoo11_addon_stock_inventory_discrepancy-11.0.1.0.0.99.dev4.dist-info/METADATA
odoo11_addon_stock_inventory_discrepancy-11.0.1.0.0.99.dev4.dist-info/WHEEL
odoo11_addon_stock_inventory_discrepancy-11.0.1.0.0.99.dev4.dist-info/top_level.txt
odoo11_addon_stock_inventory_discrepancy-11.0.1.0.0.99.dev4.dist-info/RECORD
